KratosMultiphysics/OptimizationApplication/__init__.py
KratosMultiphysics/OptimizationApplication/analyses_controller.py
KratosMultiphysics/OptimizationApplication/controls_controller.py
KratosMultiphysics/OptimizationApplication/model_parts_controller.py
KratosMultiphysics/OptimizationApplication/optimization_analysis.py
KratosMultiphysics/OptimizationApplication/optimizations_controller.py
KratosMultiphysics/OptimizationApplication/optimizer.py
KratosMultiphysics/OptimizationApplication/responses_controller.py
KratosMultiphysics/OptimizationApplication/algorithms/NLOPT_algorithms.py
KratosMultiphysics/OptimizationApplication/algorithms/SciPy_algorithms.py
KratosMultiphysics/OptimizationApplication/algorithms/__init__.py
KratosMultiphysics/OptimizationApplication/algorithms/algorithm.py
KratosMultiphysics/OptimizationApplication/algorithms/algorithm_base.py
KratosMultiphysics/OptimizationApplication/algorithms/algorithm_gradient_projection.py
KratosMultiphysics/OptimizationApplication/algorithms/algorithm_momentum_relaxed_gradient_projection.py
KratosMultiphysics/OptimizationApplication/algorithms/algorithm_nesterov_accelarated_gradient.py
KratosMultiphysics/OptimizationApplication/algorithms/algorithm_relaxed_gradient_projection.py
KratosMultiphysics/OptimizationApplication/algorithms/algorithm_steepest_descent.py
KratosMultiphysics/OptimizationApplication/algorithms/standardized_NLOPT_constraint.py
KratosMultiphysics/OptimizationApplication/algorithms/standardized_NLOPT_objective.py
KratosMultiphysics/OptimizationApplication/algorithms/standardized_SciPy_constraint.py
KratosMultiphysics/OptimizationApplication/algorithms/standardized_SciPy_objective.py
KratosMultiphysics/OptimizationApplication/algorithms/standardized_constraint.py
KratosMultiphysics/OptimizationApplication/algorithms/standardized_objective.py
KratosMultiphysics/OptimizationApplication/algorithms/standardized_rgp_constraint.py
KratosMultiphysics/OptimizationApplication/controls/control.py
kratosoptimizationapplication-10.4.0.dist-info/METADATA
kratosoptimizationapplication-10.4.0.dist-info/WHEEL
kratosoptimizationapplication-10.4.0.dist-info/RECORD
